{
  "resourceType" : "ConceptMap",
  "id" : "CMVFraceCategory",
  "text" : {
    "status" : "extensions",
    "div" : "<div xmlns=\"http://www.w3.org/1999/xhtml\"><p>Mapping from <a href=\"ValueSet-VSVFraceCategory-vista.html\">VF_raceCategory VistA</a> to <a href=\"ValueSet-VSVFraceCategory.html\">VF_raceCategory</a></p><p>DRAFT. Published on 2024-04-03 08:58:56+0000 by VA (VA: <a href=\"https://www.va.gov\">https://www.va.gov</a>). </p><div><p>Terminology Maps VF_raceCategory</p>\n</div><br/><p><b>Group 1</b>Mapping from <code>http://va.gov/terminology/vistaDefinedTerms/2-2</code> to <a href=\"http://terminology.hl7.org/3.1.0/CodeSystem-v3-NullFlavor.html\">NullFlavor</a></p><table class=\"grid\"><tr><td><b>Source Code</b></td><td><b>Relationship</b></td><td><b>Target Code</b></td></tr><tr><td>7 (*Unknown at this time*)</td><td><a href=\"http://hl7.org/fhir/R4/codesystem-concept-map-equivalence.html#equal\" title=\"equal\">is equal to</a></td><td>UNK (unknown)</td></tr><tr><td>D (DECLINED TO ANSWER)</td><td><a href=\"http://hl7.org/fhir/R4/codesystem-concept-map-equivalence.html#wider\" title=\"wider\">maps to wider concept</a></td><td>ASKU (asked but unknown)</td></tr><tr><td>U (UNKNOWN BY PATIENT)</td><td><a href=\"http://hl7.org/fhir/R4/codesystem-concept-map-equivalence.html#wider\" title=\"wider\">maps to wider concept</a></td><td>ASKU (asked but unknown)</td></tr></table><hr/><p><b>Group 2</b>Mapping from <code>http://va.gov/terminology/vistaDefinedTerms/2-2</code> to <a href=\"http://terminology.hl7.org/3.1.0/CodeSystem-CDCREC.html\">CDC Race and Ethnicity</a></p><table class=\"grid\"><tr><td><b>Source Code</b></td><td><b>Relationship</b></td><td><b>Target Code</b></td></tr><tr><td>3 (AMERICAN INDIAN OR ALASKA NATIVE)</td><td><a href=\"http://hl7.org/fhir/R4/codesystem-concept-map-equivalence.html#equal\" title=\"equal\">is equal to</a></td><td>1002-5 (American Indian or Alaska Native)</td></tr><tr><td>B (BLACK OR AFRICAN AMERICAN)</td><td><a href=\"http://hl7.org/fhir/R4/codesystem-concept-map-equivalence.html#equal\" title=\"equal\">is equal to</a></td><td>2054-5 (Black or African American)</td></tr><tr><td>H (NATIVE HAWAIIAN OR OTHER PACIFIC ISLANDER)</td><td><a href=\"http://hl7.org/fhir/R4/codesystem-concept-map-equivalence.html#equal\" title=\"equal\">is equal to</a></td><td>2076-8 (Native Hawaiian or Other Pacific Islander)</td></tr><tr><td>W (WHITE)</td><td><a href=\"http://hl7.org/fhir/R4/codesystem-concept-map-equivalence.html#equal\" title=\"equal\">is equal to</a></td><td>2106-3 (White)</td></tr><tr><td>6 (WHITE NOT OF HISP ORIG)</td><td><a href=\"http://hl7.org/fhir/R4/codesystem-concept-map-equivalence.html#equal\" title=\"equal\">is equal to</a></td><td>2106-3 (White)</td></tr></table></div>"
  },
  "url" : "http://va.gov/fhir/ConceptMap/CMVFraceCategory",
  "version" : "0.36.0",
  "name" : "VF_raceCategory",
  "title" : "VF_raceCategory",
  "status" : "draft",
  "experimental" : false,
  "date" : "2024-04-03T08:58:56+00:00",
  "publisher" : "VA",
  "contact" : [{
    "name" : "VA",
    "telecom" : [{
      "system" : "url",
      "value" : "https://www.va.gov"
    }]
  }],
  "description" : "Terminology Maps VF_raceCategory",
  "jurisdiction" : [{
    "coding" : [{
      "system" : "urn:iso:std:iso:3166",
      "code" : "US",
      "display" : "United States of America"
    }]
  }],
  "sourceCanonical" : "http://va.gov/fhir/ValueSet/VSVFraceCategory-vista",
  "targetCanonical" : "http://va.gov/fhir/ValueSet/VSVFraceCategory",
  "group" : [{
    "source" : "http://va.gov/terminology/vistaDefinedTerms/2-2",
    "target" : "http://terminology.hl7.org/CodeSystem/v3-NullFlavor",
    "element" : [{
      "code" : "7",
      "display" : "*Unknown at this time*",
      "target" : [{
        "modifierExtension" : [{
          "url" : "http://hl7.org/fhir/1.0/StructureDefinition/extension-ConceptMap.element.target.equivalence",
          "valueCode" : "equal"
        }],
        "code" : "UNK",
        "equivalence" : "equal"
      }]
    },
    {
      "code" : "D",
      "display" : "DECLINED TO ANSWER",
      "target" : [{
        "modifierExtension" : [{
          "url" : "http://hl7.org/fhir/1.0/StructureDefinition/extension-ConceptMap.element.target.equivalence",
          "valueCode" : "wider"
        }],
        "code" : "ASKU",
        "equivalence" : "wider"
      }]
    },
    {
      "code" : "U",
      "display" : "UNKNOWN BY PATIENT",
      "target" : [{
        "modifierExtension" : [{
          "url" : "http://hl7.org/fhir/1.0/StructureDefinition/extension-ConceptMap.element.target.equivalence",
          "valueCode" : "wider"
        }],
        "code" : "ASKU",
        "equivalence" : "wider"
      }]
    }]
  },
  {
    "source" : "http://va.gov/terminology/vistaDefinedTerms/2-2",
    "target" : "urn:oid:2.16.840.1.113883.6.238",
    "element" : [{
      "code" : "3",
      "display" : "AMERICAN INDIAN OR ALASKA NATIVE",
      "target" : [{
        "modifierExtension" : [{
          "url" : "http://hl7.org/fhir/1.0/StructureDefinition/extension-ConceptMap.element.target.equivalence",
          "valueCode" : "equal"
        }],
        "code" : "1002-5",
        "equivalence" : "equal"
      }]
    },
    {
      "code" : "B",
      "display" : "BLACK OR AFRICAN AMERICAN",
      "target" : [{
        "modifierExtension" : [{
          "url" : "http://hl7.org/fhir/1.0/StructureDefinition/extension-ConceptMap.element.target.equivalence",
          "valueCode" : "equal"
        }],
        "code" : "2054-5",
        "equivalence" : "equal"
      }]
    },
    {
      "code" : "H",
      "display" : "NATIVE HAWAIIAN OR OTHER PACIFIC ISLANDER",
      "target" : [{
        "modifierExtension" : [{
          "url" : "http://hl7.org/fhir/1.0/StructureDefinition/extension-ConceptMap.element.target.equivalence",
          "valueCode" : "equal"
        }],
        "code" : "2076-8",
        "equivalence" : "equal"
      }]
    },
    {
      "code" : "W",
      "display" : "WHITE",
      "target" : [{
        "modifierExtension" : [{
          "url" : "http://hl7.org/fhir/1.0/StructureDefinition/extension-ConceptMap.element.target.equivalence",
          "valueCode" : "equal"
        }],
        "code" : "2106-3",
        "equivalence" : "equal"
      }]
    },
    {
      "code" : "6",
      "display" : "WHITE NOT OF HISP ORIG",
      "target" : [{
        "modifierExtension" : [{
          "url" : "http://hl7.org/fhir/1.0/StructureDefinition/extension-ConceptMap.element.target.equivalence",
          "valueCode" : "equal"
        }],
        "code" : "2106-3",
        "equivalence" : "equal"
      }]
    }]
  }]
}