{
  "resourceType" : "ValueSet",
  "id" : "ImmunizationReaction-vista",
  "text" : {
    "status" : "generated",
    "div" : "<div xmlns=\"http://www.w3.org/1999/xhtml\"><p class=\"res-header-id\"><b>Generated Narrative: ValueSet ImmunizationReaction-vista</b></p><a name=\"ImmunizationReaction-vista\"> </a><a name=\"hcImmunizationReaction-vista\"> </a><a name=\"ImmunizationReaction-vista-en-US\"> </a><ul><li>Include these codes as defined in <code>http://va.gov/terminology/vistaDefinedElements/9000010.11-.06</code><table class=\"none\"><tr><td style=\"white-space:nowrap\"><b>Code</b></td><td><b>Display</b></td><td><b><a href=\"ValueSet-ImmunizationReaction.html\">VF_ImmunizationReaction</a></b></td></tr><tr><td>9</td><td>ANAPHYLAXIS OR COLLAPSE</td><td><span title=\"EQUIVALENT\">~</span><a href=\"http://snomed.info/id/293104008\">293104008</a></td></tr><tr><td>8</td><td>ARTHRITIS OR ARTHRALGIAS</td><td><span title=\"EQUIVALENT\">~</span><a href=\"http://snomed.info/id/293104008\">293104008</a></td></tr><tr><td>7</td><td>CONVULSIONS</td><td><span title=\"EQUIVALENT\">~</span><a href=\"http://snomed.info/id/91175000\">91175000</a></td></tr><tr><td>1</td><td>FEVER</td><td><span title=\"EQUIVALENT\">~</span><a href=\"http://snomed.info/id/386661006\">386661006</a></td></tr><tr><td>2</td><td>IRRITABILITY</td><td><span title=\"EQUIVALENT\">~</span><a href=\"http://snomed.info/id/55929007\">55929007</a></td></tr><tr><td>6</td><td>LETHARGY</td><td><span title=\"EQUIVALENT\">~</span><a href=\"http://snomed.info/id/214264003\">214264003</a></td></tr><tr><td>3</td><td>LOCAL REACTION OR SWELLING</td><td><span title=\"EQUIVALENT\">~</span><a href=\"http://snomed.info/id/293104008\">293104008</a></td></tr><tr><td>11</td><td>OTHER</td><td><span title=\"EQUIVALENT\">~</span><a href=\"http://snomed.info/id/293104008\">293104008</a></td></tr><tr><td>5</td><td>RASH OR ITCHING</td><td><span title=\"EQUIVALENT\">~</span><a href=\"http://snomed.info/id/293104008\">293104008</a></td></tr><tr><td>10</td><td>RESPIRATORY DISTRESS</td><td><span title=\"EQUIVALENT\">~</span><a href=\"http://snomed.info/id/271825005\">271825005</a></td></tr><tr><td>4</td><td>VOMITING</td><td><span title=\"EQUIVALENT\">~</span><a href=\"http://snomed.info/id/422400008\">422400008</a></td></tr><tr><td>0</td><td>NONE</td><td><span title=\"EQUIVALENT\">~</span><a href=\"https://loinc.org/LA137-2/\">LA137-2</a></td></tr></table></li></ul></div>"
  },
  "url" : "http://va.gov/fhir/ValueSet/ImmunizationReaction-vista",
  "version" : "1.5.23",
  "name" : "ImmunizationReaction_VistA",
  "title" : "ImmunizationReaction VistA",
  "status" : "active",
  "experimental" : false,
  "date" : "2025-05-23T16:28:56+00:00",
  "publisher" : "VA",
  "contact" : [{
    "name" : "VA",
    "telecom" : [{
      "system" : "url",
      "value" : "https://www.va.gov"
    }]
  }],
  "description" : "VistA Source ValueSet for Terminology Maps [VF_ImmunizationReaction](ConceptMap-VF-ImmunizationReaction.html)",
  "jurisdiction" : [{
    "coding" : [{
      "system" : "urn:iso:std:iso:3166",
      "code" : "US",
      "display" : "United States of America"
    }]
  }],
  "compose" : {
    "include" : [{
      "system" : "http://va.gov/terminology/vistaDefinedElements/9000010.11-.06",
      "concept" : [{
        "code" : "9",
        "display" : "ANAPHYLAXIS OR COLLAPSE"
      },
      {
        "code" : "8",
        "display" : "ARTHRITIS OR ARTHRALGIAS"
      },
      {
        "code" : "7",
        "display" : "CONVULSIONS"
      },
      {
        "code" : "1",
        "display" : "FEVER"
      },
      {
        "code" : "2",
        "display" : "IRRITABILITY"
      },
      {
        "code" : "6",
        "display" : "LETHARGY"
      },
      {
        "code" : "3",
        "display" : "LOCAL REACTION OR SWELLING"
      },
      {
        "code" : "11",
        "display" : "OTHER"
      },
      {
        "code" : "5",
        "display" : "RASH OR ITCHING"
      },
      {
        "code" : "10",
        "display" : "RESPIRATORY DISTRESS"
      },
      {
        "code" : "4",
        "display" : "VOMITING"
      },
      {
        "code" : "0",
        "display" : "NONE"
      }]
    }]
  }
}